

<methods>
	<method>
		<name>each</name>
		<class>Integer</class>
		<class>Array</class>
		<class>Hash</class>
		<count>48</count>
	</method>
	<method>
		<name>each</name>
		<class>Integer</class>
		<class>Array</class>
		<class>Hash</class>
		<count>48</count>
	</method>
	<method>
		<name>each</name>
		<class>Integer</class>
		<class>Array</class>
		<class>Hash</class>
		<count>48</count>
	</method>
	<method>
		<name>each</name>
		<class>Integer</class>
		<class>Array</class>
		<class>Hash</class>
		<count>48</count>
	</method>
</methods>